{"airlines":[{"iata":"5O","icao":null,"nvls":5082,"publicName":"ASL Airlines France"},{"iata":"JP","icao":"ADR","nvls":6,"publicName":"Adria Airways"},{"iata":"A3","icao":"AEE","nvls":386,"publicName":"Aegean Airlines"},{"iata":"EI","icao":"EIN","nvls":108,"publicName":"Aer Lingus"},{"iata":null,"icao":null,"nvls":5086,"publicName":"AerCap Ireland Ltd."},{"iata":"SU","icao":"AFL","nvls":7,"publicName":"Aeroflot"},{"iata":"AM","icao":"AMX","nvls":794,"publicName":"Aeromexico"},{"iata":null,"icao":"IAM","nvls":5140,"publicName":"Aeronautica Militare Italiana"},{"iata":null,"icao":"DFC","nvls":5125,"publicName":"Aeropartner"},{"iata":"3O","icao":"MAC","nvls":4891,"publicName":"Air Arabia Maroc"},{"iata":"KC","icao":"KZR","nvls":392,"publicName":"Air Astana"},{"iata":"UU","icao":"REU","nvls":3615,"publicName":"Air Austral"},{"iata":"SM","icao":"MSC","nvls":4828,"publicName":"Air Cairo"},{"iata":"AC","icao":"ACA","nvls":54,"publicName":"Air Canada"},{"iata":"UX","icao":"AEA","nvls":519,"publicName":"Air Europa"},{"iata":"AF","icao":"AFR","nvls":80,"publicName":"Air France"},{"iata":"AI","icao":"AIC","nvls":712,"publicName":"Air India"},{"iata":"KM","icao":"AMC","nvls":117,"publicName":"Air Malta"},{"iata":"MK","icao":"MAU","nvls":2867,"publicName":"Air Mauritius"},{"iata":"YW","icao":"ANS","nvls":284,"publicName":"Air Nostrum"},{"iata":"JU","icao":"ASL","nvls":98,"publicName":"Air Serbia"},{"iata":"TS","icao":"TSC","nvls":169,"publicName":"Air Transat"},{"iata":"BT","icao":"BTI","nvls":419,"publicName":"AirBaltic"},{"iata":null,"icao":"AQS","nvls":5141,"publicName":"Airstream AS"},{"iata":"UJ","icao":"LMU","nvls":5092,"publicName":"AlMasria Universal Airlines"},{"iata":"JQ","icao":"LAV","nvls":4987,"publicName":"Alba Star"},{"iata":null,"icao":"ULC","nvls":5147,"publicName":"Albinati Aviation"},{"iata":"AZ","icao":"AZA","nvls":12,"publicName":"Alitalia"},{"iata":"NH","icao":"ANA","nvls":797,"publicName":"All Nippon Airways"},{"iata":"AA","icao":"AAL","nvls":555,"publicName":"American Airlines"},{"iata":"IZ","icao":"AIZ","nvls":30,"publicName":"Arkia"},{"iata":"KK","icao":"KKK","nvls":5061,"publicName":"Atlasglobal"},{"iata":"OS","icao":"AUA","nvls":21,"publicName":"Austrian Airlines"},{"iata":"1B","icao":"BGH","nvls":232,"publicName":"Balkan Holiday Airlines"},{"iata":"B2","icao":"BRU","nvls":504,"publicName":"Belavia"},{"iata":null,"icao":"BFD","nvls":5107,"publicName":"Bertelsmann"},{"iata":"BA","icao":"BAW","nvls":31,"publicName":"British Airways"},{"iata":"FB","icao":"LZB","nvls":387,"publicName":"Bulgaria Air"},{"iata":"CM","icao":"CMP","nvls":1405,"publicName":"COPA Airlines"},{"iata":"VR","icao":"TCV","nvls":162,"publicName":"Cabo Verde Airlines"},{"iata":"V3","icao":"KRP","nvls":4894,"publicName":"Carpatair"},{"iata":"CX","icao":"CPA","nvls":4826,"publicName":"Cathay Pacific"},{"iata":"CI","icao":"CAL","nvls":44,"publicName":"China Airlines"},{"iata":"MU","icao":"CES","nvls":1294,"publicName":"China Eastern Airlines"},{"iata":"CZ","icao":"CSN","nvls":43,"publicName":"China Southern Airlines"},{"iata":"WX","icao":"BCY","nvls":267,"publicName":"Cityjet"},{"iata":"XC","icao":"CAI","nvls":455,"publicName":"Corendon Airlines"},{"iata":"CD","icao":"CND","nvls":4982,"publicName":"Corendon Dutch Airlines"},{"iata":"XR","icao":"CXI","nvls":5099,"publicName":"Corendon Europe Airl"},{"iata":"OU","icao":"CTN","nvls":51,"publicName":"Croatia Airlines"},{"iata":"OK","icao":"CSA","nvls":52,"publicName":"Czech Airlines CSA"},{"iata":"DL","icao":"DAL","nvls":58,"publicName":"Delta Air Lines"},{"iata":null,"icao":"JME","nvls":5150,"publicName":"EJME Aircraft Management"},{"iata":null,"icao":"XRO","nvls":5077,"publicName":"EXXAERO INTERNATIONAL"},{"iata":"U2","icao":"EZY","nvls":64,"publicName":"EasyJet"},{"iata":null,"icao":"EJU","nvls":5151,"publicName":"EasyJet Europe"},{"iata":"DS","icao":"EZS","nvls":74,"publicName":"EasyJet Switzerland"},{"iata":"MS","icao":"MSR","nvls":65,"publicName":"Egypt Air"},{"iata":"LY","icao":"ELY","nvls":66,"publicName":"El Al"},{"iata":"EK","icao":"UAE","nvls":4913,"publicName":"Emirates"},{"iata":"ET","icao":"ETH","nvls":188,"publicName":"Ethiopian Airlines"},{"iata":"EY","icao":"ETD","nvls":274,"publicName":"Etihad Airways"},{"iata":null,"icao":"EES","nvls":5121,"publicName":"Europe Executive Jet Services"},{"iata":"EW","icao":"EWG","nvls":133,"publicName":"Eurowings"},{"iata":"BR","icao":"EVA","nvls":71,"publicName":"Eva Air"},{"iata":null,"icao":"EVL","nvls":5144,"publicName":"Evolem Aviation"},{"iata":null,"icao":"PBR","nvls":5134,"publicName":"Fast Air"},{"iata":"AY","icao":"FIN","nvls":78,"publicName":"Finnair"},{"iata":null,"icao":"VCG","nvls":5138,"publicName":"Fly Vectra"},{"iata":"BE","icao":"BEE","nvls":502,"publicName":"Flybe"},{"iata":null,"icao":"FYL","nvls":5108,"publicName":"Flying Group Luxembourg"},{"iata":"FH","icao":"FHY","nvls":190,"publicName":"Freebird Airlines"},{"iata":null,"icao":"GNJ","nvls":5127,"publicName":"Gainjet Aviation Greece"},{"iata":null,"icao":"GJI","nvls":5115,"publicName":"Gainjet Ireland"},{"iata":null,"icao":"GAJ","nvls":5126,"publicName":"Gama Charters"},{"iata":"GA","icao":"GIA","nvls":85,"publicName":"Garuda Indonesia"},{"iata":"A9","icao":"TGZ","nvls":16,"publicName":"Georgian Airlines"},{"iata":"GM","icao":"GSW","nvls":5093,"publicName":"Germania Flug AG"},{"iata":"4U","icao":"GWI","nvls":5005,"publicName":"Germanwings"},{"iata":null,"icao":"GJE","nvls":5122,"publicName":"Global Air Charters"},{"iata":"G3","icao":"GLO","nvls":4918,"publicName":"Gol Transportes Aereos"},{"iata":null,"icao":"GAG","nvls":5137,"publicName":"Greybird Pilot Academy"},{"iata":"A5","icao":"HOP","nvls":5021,"publicName":"HOP!"},{"iata":null,"icao":"HHN","nvls":5110,"publicName":"Hahn Air-Lines"},{"iata":"2L","icao":"OAW","nvls":449,"publicName":"Helvetic"},{"iata":null,"icao":"HYP","nvls":5149,"publicName":"Hyperion Aviation"},{"iata":"IB","icao":"IBE","nvls":92,"publicName":"Iberia"},{"iata":"I2","icao":"IBS","nvls":5003,"publicName":"Iberia Express"},{"iata":"FI","icao":"ICE","nvls":94,"publicName":"Icelandair"},{"iata":"IR","icao":"IRA","nvls":95,"publicName":"Iranair"},{"iata":"6H","icao":"ISR","nvls":96,"publicName":"Israir"},{"iata":"9W","icao":"JAI","nvls":2481,"publicName":"Jet Airways"},{"iata":null,"icao":null,"nvls":5130,"publicName":"Jet Aviation Netherlands B.V."},{"iata":null,"icao":null,"nvls":5129,"publicName":"Jet Aviation Netherlands B.V."},{"iata":null,"icao":"EDG","nvls":5145,"publicName":"Jet Edge"},{"iata":null,"icao":"JEI","nvls":5103,"publicName":"Jet Executive International"},{"iata":null,"icao":"JDI","nvls":5148,"publicName":"Jet Story"},{"iata":"LS","icao":"EXS","nvls":42,"publicName":"Jet2.com"},{"iata":null,"icao":"JBC","nvls":5101,"publicName":"JetBee"},{"iata":null,"icao":"KBD","nvls":5114,"publicName":"JetKey"},{"iata":null,"icao":"JMK","nvls":5105,"publicName":"JetMagic"},{"iata":"KL","icao":"KLM","nvls":100,"publicName":"KLM"},{"iata":"WA","icao":"KLC","nvls":102,"publicName":"KLM Cityhopper"},{"iata":null,"icao":"KAI","nvls":5095,"publicName":"Kaiser Air"},{"iata":"KQ","icao":"KQA","nvls":208,"publicName":"Kenya Airways"},{"iata":"KE","icao":"KAL","nvls":105,"publicName":"Korean Air"},{"iata":"VK","icao":"FOO","nvls":5142,"publicName":"LEVEL"},{"iata":"N4","icao":"NWS","nvls":5089,"publicName":"LLC Nord Wind"},{"iata":null,"icao":"LDX","nvls":5111,"publicName":"LaudaMotion Executive"},{"iata":null,"icao":"LHB","nvls":5104,"publicName":"Liebherr Geschaeftsreiseflugzeug GBR"},{"iata":"LO","icao":"LOT","nvls":111,"publicName":"Lot Polish Airlines"},{"iata":"LH","icao":"DLH","nvls":112,"publicName":"Lufthansa"},{"iata":null,"icao":"LXG","nvls":5119,"publicName":"Luxaviation Germany"},{"iata":null,"icao":"LWG","nvls":5131,"publicName":"Luxwing"},{"iata":"ME","icao":"MEA","nvls":2908,"publicName":"MEA - Middle East Airlines"},{"iata":"M2","icao":"MHV","nvls":5109,"publicName":"MHS Aviation"},{"iata":"MB","icao":"MNB","nvls":328,"publicName":"MNG Airlines"},{"iata":"MH","icao":"MAS","nvls":5064,"publicName":"Malaysia Airlines"},{"iata":null,"icao":"MLT","nvls":5079,"publicName":"Maleth-Aero"},{"iata":"NE","icao":"NMA","nvls":5091,"publicName":"Nesma Airlines"},{"iata":null,"icao":null,"nvls":5085,"publicName":"Network Airline Management"},{"iata":"D8","icao":"IBK","nvls":5081,"publicName":"Norwegian Air International"},{"iata":"DY","icao":"NAX","nvls":532,"publicName":"Norwegian Air Shuttle"},{"iata":"WY","icao":"OMA","nvls":3297,"publicName":"Oman Air"},{"iata":"8Q","icao":"OHY","nvls":137,"publicName":"Onur Air"},{"iata":null,"icao":"OTF","nvls":5136,"publicName":"Orange2fly Airlines, SA"},{"iata":"PK","icao":"PIA","nvls":140,"publicName":"Pakistan Airlines"},{"iata":"PC","icao":"PGT","nvls":139,"publicName":"Pegasus Airlines"},{"iata":"PE","icao":"PEV","nvls":5096,"publicName":"People's Vienna Line"},{"iata":null,"icao":"NTF","nvls":5133,"publicName":"Piper OK"},{"iata":null,"icao":"PVJ","nvls":5143,"publicName":"Privajet"},{"iata":null,"icao":"PWY","nvls":5113,"publicName":"Privateways Luftfahrtgesellschaft"},{"iata":"QF","icao":"QFA","nvls":205,"publicName":"Qantas Airways"},{"iata":"QR","icao":"QTR","nvls":356,"publicName":"Qatar Airways"},{"iata":"AT","icao":"RAM","nvls":145,"publicName":"Royal Air Maroc"},{"iata":"RJ","icao":"RJA","nvls":147,"publicName":"Royal Jordanian Airlines"},{"iata":null,"icao":"FRV","nvls":5106,"publicName":"Royal Moroccan Air Force"},{"iata":"FR","icao":"RYR","nvls":234,"publicName":"Ryanair"},{"iata":null,"icao":null,"nvls":5132,"publicName":"Sand Air"},{"iata":"S4","icao":"RZO","nvls":476,"publicName":"Sata International"},{"iata":"SV","icao":"SVA","nvls":151,"publicName":"Saudi Arabian Airlines"},{"iata":"AR","icao":null,"nvls":4915,"publicName":"Saudi Aramco Aviation"},{"iata":"SK","icao":"SAS","nvls":150,"publicName":"Scandinavian Airlines"},{"iata":"SQ","icao":"SIA","nvls":152,"publicName":"Singapore Airlines"},{"iata":null,"icao":"KFE","nvls":5139,"publicName":"SkyFirst"},{"iata":"SX","icao":"SRK","nvls":4030,"publicName":"Skywork Airlines"},{"iata":"P7","icao":"LLP","nvls":5080,"publicName":"Small Planet Airlines"},{"iata":"5P","icao":"LLX","nvls":5084,"publicName":"Small Planet Airlines"},{"iata":null,"icao":"MYX","nvls":5100,"publicName":"Smart Lynx Estonia"},{"iata":"6Y","icao":"ART","nvls":5088,"publicName":"SmartLynx Airlines"},{"iata":"QS","icao":"TVS","nvls":378,"publicName":"SmartWings"},{"iata":"SA","icao":"SAA","nvls":149,"publicName":"South African Airways"},{"iata":null,"icao":"SSZ","nvls":5118,"publicName":"Specsavers Aviation"},{"iata":null,"icao":"IBG","nvls":5094,"publicName":"Springfield Air"},{"iata":"UL","icao":"ALK","nvls":5051,"publicName":"SriLankan Airlines"},{"iata":null,"icao":null,"nvls":5076,"publicName":"Stecker Ltd"},{"iata":null,"icao":"FFD","nvls":5097,"publicName":"Stuttgarter Flugdienst"},{"iata":"XQ","icao":"SXS","nvls":197,"publicName":"SunExpress"},{"iata":"XG","icao":"SXD","nvls":5047,"publicName":"SunExpress Deutschland"},{"iata":"SR","icao":"SDR","nvls":5152,"publicName":"Sundair"},{"iata":null,"icao":"TWY","nvls":5117,"publicName":"Sunset Aviation"},{"iata":"PY","icao":"SLM","nvls":206,"publicName":"Surinam Airways"},{"iata":"LX","icao":"SWR","nvls":50,"publicName":"Swiss International Airlines"},{"iata":"7E","icao":"AWU","nvls":5124,"publicName":"Sylt Air"},{"iata":null,"icao":"SYG","nvls":5116,"publicName":"Synergy Aviation"},{"iata":"DT","icao":"DTA","nvls":1676,"publicName":"TAAG Angola Airlines"},{"iata":"TP","icao":"TAP","nvls":163,"publicName":"TAP Portugal"},{"iata":"TB","icao":"JAF","nvls":4807,"publicName":"TUI Airlines Belgium"},{"iata":"X3","icao":"TUI","nvls":4848,"publicName":"TUI fly"},{"iata":"OR","icao":"TFL","nvls":231,"publicName":"TUI fly"},{"iata":"6B","icao":"BLX","nvls":5135,"publicName":"TUIfly Nordic"},{"iata":"RO","icao":"ROT","nvls":239,"publicName":"Tarom"},{"iata":"TG","icao":"THA","nvls":4237,"publicName":"Thai Airways"},{"iata":"HV","icao":"TRA","nvls":164,"publicName":"Transavia"},{"iata":"TO","icao":"TVF","nvls":5048,"publicName":"Transavia France"},{"iata":"TU","icao":"TAR","nvls":171,"publicName":"Tunisair"},{"iata":"TK","icao":"THY","nvls":166,"publicName":"Turkish Airlines"},{"iata":null,"icao":"CMB","nvls":5153,"publicName":"US Transportation Command"},{"iata":"PS","icao":"AUI","nvls":175,"publicName":"Ukraine Int. Airlines"},{"iata":"UA","icao":"UAL","nvls":179,"publicName":"United Airlines"},{"iata":"NN","icao":"MOV","nvls":5090,"publicName":"VIM Airlines"},{"iata":"VN","icao":"HVN","nvls":2328,"publicName":"Vietnam Airlines"},{"iata":"VS","icao":"VIR","nvls":181,"publicName":"Virgin Atlantic"},{"iata":null,"icao":"VJT","nvls":5102,"publicName":"VistaJet"},{"iata":"V7","icao":"VOE","nvls":5112,"publicName":"Volotea"},{"iata":"VY","icao":"VLG","nvls":263,"publicName":"Vueling"},{"iata":"WW","icao":"WOW","nvls":5020,"publicName":"WOW Air"},{"iata":null,"icao":"WGN","nvls":5083,"publicName":"Western Global Airlines"},{"iata":null,"icao":"WJT","nvls":5078,"publicName":"Wijet"},{"iata":"7W","icao":"WRC","nvls":4927,"publicName":"Wind Rose Aviation"},{"iata":null,"icao":null,"nvls":5098,"publicName":"World Fuel Services Corporative Aviation Supprt SV"},{"iata":null,"icao":"WWI","nvls":5146,"publicName":"Worldwide Jet Charter"},{"iata":null,"icao":"XJC","nvls":5120,"publicName":"Xclusive Jet Charter"},{"iata":"MF","icao":"CXA","nvls":1551,"publicName":"Xiamen Airlines"},{"iata":"Z4","icao":"GZQ","nvls":5044,"publicName":"Zagrosjet"},{"iata":null,"icao":"BZE","nvls":5123,"publicName":"Zenith Aviation"}]}